README.rst
setup.py
quickunit/__init__.py
quickunit/diff.py
quickunit/filechecker.py
quickunit/plugin.py
quickunit/utils.py
quickunit.egg-info/PKG-INFO
quickunit.egg-info/SOURCES.txt
quickunit.egg-info/dependency_links.txt
quickunit.egg-info/entry_points.txt
quickunit.egg-info/not-zip-safe
quickunit.egg-info/requires.txt
quickunit.egg-info/top_level.txt
quickunit/scripts/__init__.py
quickunit/scripts/finder.py
quickunit/vcs/__init__.py
quickunit/vcs/base.py
quickunit/vcs/git.py
quickunit/vcs/hg.py
tests/quickunit/__init__.py
tests/quickunit/test_filechecker.py