Metadata-Version: 1.1
Name: quickunit
Version: 0.6.0
Summary: A discovery plugin for Nose which relies on sane structure.
Home-page: http://github.com/dcramer/quickunit
Author: David Cramer
Author-email: dcramer@gmail.com
License: Apache License 2.0
Platform: UNKNOWN
Classifier: Intended Audience :: Developers
Classifier: Intended Audience :: System Administrators
Classifier: Operating System :: OS Independent
Classifier: Topic :: Software Development
